neurodb/__init__.py
neurodb/main.py
neurodb-0.0.1.dist-info/METADATA
neurodb-0.0.1.dist-info/WHEEL
neurodb-0.0.1.dist-info/licenses/LICENSE
neurodb-0.0.1.dist-info/RECORD
