Metadata-Version: 2.4
Name: neurodb
Version: 0.0.1
Summary:     A smart and efficient database orchestration layer that simplifies multi-database     interactions with intuitive operations and seamless Pandas integration.
Project-URL: Homepage, https://github.com/dion-gory/neurodb
Project-URL: Bug Tracker, https://github.com/dion-gory/neurodb/issues
Author-email: Dion Gory <diongory@gmail.com>
License-File: LICENSE
Classifier: License :: OSI Approved :: Apache Software License
Classifier: Operating System :: OS Independent
Classifier: Programming Language :: Python :: 3
Requires-Python: >=3.12
